Metadata-Version: 1.1
Name: hex2
Version: 2.2.0
Summary: Hexdump command line utility.
Home-page: https://github.com/yafeile/hex
Author: yafeile
Author-email: yafeile@sohu.com
License: Public Domain
Platform: UNKNOWN
Classifier: Development Status :: 5 - Production/Stable
Classifier: Programming Language :: Python :: 2
Classifier: Operating System :: OS Independent
Classifier: License :: Public Domain
Classifier: Topic :: Utilities
